snir/__init__.py
snir-0.1.1.dist-info/METADATA
snir-0.1.1.dist-info/WHEEL
snir-0.1.1.dist-info/top_level.txt
snir-0.1.1.dist-info/RECORD
